greeter/__init__.py
greeter/__main__.py
greeter/config.yml
greeter/greeter.py
greeter_source_code/__init__.py
greeter_source_code/__main__.py
greeter_source_code/greeter.py
greeter_sarasa-2.1.1.dist-info/METADATA
greeter_sarasa-2.1.1.dist-info/WHEEL
greeter_sarasa-2.1.1.dist-info/entry_points.txt
greeter_sarasa-2.1.1.dist-info/top_level.txt
greeter_sarasa-2.1.1.dist-info/RECORD
