Metadata-Version: 2.1
Name: greeter-sarasa
Version: 2.1.1
Summary: Greets people
Home-page: https://gitlab.com/maartincm/greeter
Author: Martin Cuesta
Author-email: cuesta.martin.n@hotmail.com
License: MIT
Platform: UNKNOWN
Classifier: License :: OSI Approved :: MIT License
Classifier: Programming Language :: Python :: 3
Classifier: Programming Language :: Python :: 3.7
Requires-Dist: PyYAML (==5.3.1)
